Metadata-Version: 2.1
Name: PySquareRoot
Version: 0.0.1
Summary: Simple Square Root package.
Home-page: UNKNOWN
Author: ProfMYK
Author-email: <mykomurcu1@gmail.com>
License: UNKNOWN
Keywords: python,math,squareRoot
Platform: UNKNOWN
Classifier: Development Status :: 1 - Planning
Classifier: Intended Audience :: Developers
Classifier: Programming Language :: Python :: 3
Classifier: Operating System :: Unix
Classifier: Operating System :: MacOS :: MacOS X
Classifier: Operating System :: Microsoft :: Windows
